pyAudioDspTools/EffectCompressor.py
pyAudioDspTools/EffectDelay.py
pyAudioDspTools/EffectEQ3Band.py
pyAudioDspTools/EffectEQ3BandFFT.py
pyAudioDspTools/EffectEQ3BandFFTGPU.py
pyAudioDspTools/EffectFFTFilter.py
pyAudioDspTools/EffectFFTFilterGPU.py
pyAudioDspTools/EffectGate.py
pyAudioDspTools/EffectHardDistortion.py
pyAudioDspTools/EffectSaturator.py
pyAudioDspTools/EffectSoftClipper.py
pyAudioDspTools/EffectTremolo.py
pyAudioDspTools/Generators.py
pyAudioDspTools/Utility.py
pyAudioDspTools/_EffectBitCrusher.py
pyAudioDspTools/_EffectReverb.py
pyAudioDspTools/__init__.py
pyAudioDspTools/config.py
pyaudiodsptools-0.8.3.dist-info/LICENSE
pyaudiodsptools-0.8.3.dist-info/METADATA
pyaudiodsptools-0.8.3.dist-info/WHEEL
pyaudiodsptools-0.8.3.dist-info/top_level.txt
pyaudiodsptools-0.8.3.dist-info/RECORD
