Metadata-Version: 2.2
Name: pyAudioDspTools
Version: 0.8.3
Summary: Package for audio processing with Numpy
Home-page: https://github.com/ArjaanAuinger/pyaudiodsptools
Author: Arjaan Auinger
Author-email: arjaan.auinger@gmail.com
License: MIT License
Requires-Python: >=3.6
License-File: LICENSE
Requires-Dist: numpy
Dynamic: author
Dynamic: author-email
Dynamic: description
Dynamic: home-page
Dynamic: license
Dynamic: requires-dist
Dynamic: requires-python
Dynamic: summary
